MANIFEST.in
README.rst
setup.py
django_errortemplates.egg-info/PKG-INFO
django_errortemplates.egg-info/SOURCES.txt
django_errortemplates.egg-info/dependency_links.txt
django_errortemplates.egg-info/not-zip-safe
django_errortemplates.egg-info/requires.txt
django_errortemplates.egg-info/top_level.txt
errortemplates/__init__.py
errortemplates/models.py
errortemplates/static/errortemplates/style.css
errortemplates/templates/404.html
errortemplates/templates/500.html