Metadata-Version: 1.0
Name: django-errortemplates
Version: 1.0
Summary: Django error page templates (404.html and 500.html).
Home-page: https://github.com/espenak/django_errortemplates
Author: Espen Angell Kristiansen
Author-email: UNKNOWN
License: BSD
Platform: UNKNOWN
Classifier: Development Status :: 5 - Production/Stable
Classifier: Environment :: Web Environment
Classifier: Framework :: Django
Classifier: Intended Audience :: Developers
Classifier: License :: OSI Approved
Classifier: Operating System :: OS Independent
Classifier: Programming Language :: Python
